soundcloud_cli
