Metadata-Version: 1.1
Name: soundcloud-cli
Version: 0.2.5
Summary: Soundcloud command-line utility
Home-page: https://github.com/zeekay/soundcloud-cli
Author: Zach Kelling
Author-email: zk@monoid.io
License: MIT
Keywords: commandline cli soundcloud music upload utility
Platform: UNKNOWN
Classifier: Development Status :: 5 - Production/Stable
Classifier: Programming Language :: Python :: 2.7
Classifier: Programming Language :: Python :: 3.3
Classifier: Programming Language :: Python :: 3.4
Classifier: License :: OSI Approved :: MIT License
